README.md
pocket.py
setup.py
pocket_dictionary.egg-info/PKG-INFO
pocket_dictionary.egg-info/SOURCES.txt
pocket_dictionary.egg-info/dependency_links.txt
pocket_dictionary.egg-info/top_level.txt